locationcrypto/__init__.py
locationcrypto/crypt.py
locationcrypto-1.0.9.dist-info/LICENSE
locationcrypto-1.0.9.dist-info/METADATA
locationcrypto-1.0.9.dist-info/WHEEL
locationcrypto-1.0.9.dist-info/top_level.txt
locationcrypto-1.0.9.dist-info/RECORD
