Metadata-Version: 2.1
Name: locationcrypto
Version: 1.0.9
Summary: Location based Cryptography uses location of the device in addition to the pass-phrase as key.
Home-page: https://github.com/harshildarji/locationcrypto
Author: Harshil Darji
Author-email: darjiharshil2994@gmail.com
License: UNKNOWN
Platform: UNKNOWN
Classifier: Programming Language :: Python :: 3
Classifier: License :: OSI Approved :: MIT License
Classifier: Operating System :: OS Independent
Requires-Python: >=3.6
Requires-Dist: geocoder
